{"cameraMode":{"drawMode":0,"name":"Shaded","section":"Shading Mode"},"sceneLighting":true,"audioPlay":false,"sceneViewState":{"m_AlwaysRefresh":false,"showFog":true,"showSkybox":true,"showFlares":true,"showImageEffects":true,"showParticleSystems":true,"showVisualEffectGraphs":true,"m_FxEnabled":true},"in2DMode":false,"pivot":{"x":-4.852823257446289,"y":-71.95966339111328,"z":57.61767578125},"rotation":{"x":0.4095489978790283,"y":-0.14541420340538026,"z":0.06630521267652512,"w":0.8981883525848389},"size":68.52049255371094,"orthographic":false}